pointofview/__init__.py
pointofview/py.typed
pointofview-1.1.3.dist-info/METADATA
pointofview-1.1.3.dist-info/WHEEL
pointofview-1.1.3.dist-info/licenses/LICENSE
pointofview-1.1.3.dist-info/RECORD
