Metadata-Version: 2.4
Name: pointofview
Version: 1.1.3
Summary: A Python package for determining a piece of text's point of view (first, second, third, or unknown).
License-Expression: GPL-3.0-or-later
License-File: LICENSE
Keywords: point of view,text analysis,natural language processing
Author: David L. Day
Author-email: david@davidlday.com
Requires-Python: >=3.9,<4.0
Classifier: Development Status :: 5 - Production/Stable
Classifier: Intended Audience :: Developers
Classifier: License :: OSI Approved :: GNU General Public License v3 (GPLv3)
Classifier: Natural Language :: English
Classifier: Operating System :: OS Independent
Classifier: Programming Language :: Python :: 3
Classifier: Programming Language :: Python :: 3.9
Classifier: Programming Language :: Python :: 3.10
Classifier: Programming Language :: Python :: 3.11
Classifier: Programming Language :: Python :: 3.12
Classifier: Programming Language :: Python :: 3.13
Classifier: Programming Language :: Python :: 3.14
Classifier: Programming Language :: Python :: 3.7
Classifier: Programming Language :: Python :: 3.8
Classifier: Topic :: Software Development :: Libraries :: Python Modules
Classifier: Topic :: Text Processing :: Linguistic
Classifier: Typing :: Typed
Requires-Dist: importlib-metadata (>=5.1,<7.0)
Project-URL: Homepage, https://github.com/prosegrinder/python-pointofview
Project-URL: Repository, https://github.com/prosegrinder/python-pointofview
